LICENSE
MANIFEST.in
README.md
VERSION
setup.py
VMR/README.md
pyctv_lib/__init__.py
pyctv_lib/colours.py
pyctv_lib/helper.py
pyctv_lib/parse_vmr.py
pyctv_lib/pyctv.py
pyctv_lib/update_vmr.py
pyctv_lib/version.py
pyctv_lib/vmr.py
pyctv_lib/vmr_error.py
pyctv_taxonomy.egg-info/PKG-INFO
pyctv_taxonomy.egg-info/SOURCES.txt
pyctv_taxonomy.egg-info/dependency_links.txt
pyctv_taxonomy.egg-info/entry_points.txt
pyctv_taxonomy.egg-info/requires.txt
pyctv_taxonomy.egg-info/top_level.txt