Metadata-Version: 2.1
Name: pyctv-taxonomy
Version: 0.25
Summary: Download ICTV Virus Classifications as Python Objects
Home-page: https://github.com/linsalrob/pyctv
Author: Rob Edwards
Author-email: raedwards@gmail.com
License: The MIT License (MIT)
Keywords: phage virus bioinformatics microbiology bacteria genome genomics
Platform: any
Classifier: Development Status :: 4 - Beta
Classifier: Intended Audience :: Science/Research
Classifier: License :: OSI Approved :: MIT License
Classifier: Natural Language :: English
Classifier: Operating System :: MacOS :: MacOS X
Classifier: Operating System :: POSIX :: Linux
Classifier: Operating System :: Unix
Classifier: Programming Language :: Python :: 3.0
Classifier: Topic :: Scientific/Engineering :: Bio-Informatics
